CHANGES.rst
MANIFEST.in
setup.py
Products/__init__.py
Products.PloneHotfix20160830.egg-info/PKG-INFO
Products.PloneHotfix20160830.egg-info/SOURCES.txt
Products.PloneHotfix20160830.egg-info/dependency_links.txt
Products.PloneHotfix20160830.egg-info/entry_points.txt
Products.PloneHotfix20160830.egg-info/namespace_packages.txt
Products.PloneHotfix20160830.egg-info/not-zip-safe
Products.PloneHotfix20160830.egg-info/requires.txt
Products.PloneHotfix20160830.egg-info/top_level.txt
Products/PloneHotfix20160830/README.txt
Products/PloneHotfix20160830/__init__.py
Products/PloneHotfix20160830/confirm.py
Products/PloneHotfix20160830/discussion.py
Products/PloneHotfix20160830/in_portal.py
Products/PloneHotfix20160830/plonerootlogin.py
Products/PloneHotfix20160830/redirect_folderfactories.py
Products/PloneHotfix20160830/redirect_qi.py
Products/PloneHotfix20160830/redirects.py
Products/PloneHotfix20160830/redirectto.py
Products/PloneHotfix20160830/resource.py
Products/PloneHotfix20160830/user.py
Products/PloneHotfix20160830/utils.py
Products/PloneHotfix20160830/z3c_form.py
Products/PloneHotfix20160830/zmi.py
Products/PloneHotfix20160830/www/manageTransientObjectContainer.dtml
Products/PloneHotfix20160830/www/manage_tabs.dtml
docs/LICENSE.GPL
docs/LICENSE.txt