Metadata-Version: 1.1
Name: Products.PloneHotfix20160830
Version: 1.1
Summary: Various Plone hotfixes, 2016-08-30
Home-page: https://github.com/plone
Author: Plone Security Team
Author-email: security@plone.org
License: GPL
Keywords: plone security hotfix patch
Platform: UNKNOWN
Classifier: Framework :: Plone
Classifier: Programming Language :: Python
